incremental/__init__.py
incremental/handler.py
incremental/processor.py
incremental_progress-1.1.0.dist-info/METADATA
incremental_progress-1.1.0.dist-info/WHEEL
incremental_progress-1.1.0.dist-info/entry_points.txt
incremental_progress-1.1.0.dist-info/top_level.txt
incremental_progress-1.1.0.dist-info/RECORD
