Metadata-Version: 2.1
Name: incremental-progress
Version: 1.1.0
Summary: Teaching tool for recording development steps
Home-page: https://github.com/taosdevops/incremental-progress
Author: TAOS DevopsNow
Author-email: devopsnow@taos.com
License: UNKNOWN
Platform: UNKNOWN
Classifier: Programming Language :: Python :: 3
Classifier: License :: OSI Approved :: GNU General Public License v3 or later (GPLv3+)
Classifier: Operating System :: OS Independent
Requires-Python: >=3.6
Requires-Dist: watchgod (==0.5)
